qosm/__init__.py
qosm/__main__.py
qosm/__version__.py
qosm/_core.cpython-312-x86_64-linux-gnu.so
qosm/libopenblas.dll
qosm/gui/__init__.py
qosm/gui/gui.py
qosm/gui/dialogs/GifExportDialog.py
qosm/gui/dialogs/__init__.py
qosm/gui/dialogs/objects/DomainDialog.py
qosm/gui/dialogs/objects/GBEGridCreateDialog.py
qosm/gui/dialogs/objects/GBTCPortDialog.py
qosm/gui/dialogs/objects/LensDialog.py
qosm/gui/dialogs/objects/MultiLayerSampleCreateDialog.py
qosm/gui/dialogs/objects/ShapeDialog.py
qosm/gui/dialogs/objects/StepLoadDialog.py
qosm/gui/dialogs/requests/FFCreateDialog.py
qosm/gui/dialogs/requests/GBTCRequestCreateDialog.py
qosm/gui/dialogs/requests/NFGridGreateDialog.py
qosm/gui/dialogs/requests/PipelineDialog.py
qosm/gui/dialogs/requests/SetSweepDialog.py
qosm/gui/dialogs/sources/GaussianBeamCreateDialog.py
qosm/gui/dialogs/sources/HornCreateDialog.py
qosm/gui/dialogs/sources/NFSourceDialog.py
qosm/gui/managers/GBTCSimulationManager.py
qosm/gui/managers/ObjectManager.py
qosm/gui/managers/RequestManager.py
qosm/gui/managers/ResultViewManager.py
qosm/gui/managers/SimulationManager.py
qosm/gui/managers/SourceManager.py
qosm/gui/managers/__init__.py
qosm/gui/objects/Feko.py
qosm/gui/objects/Ticra.py
qosm/gui/objects/__init__.py
qosm/gui/objects/hdf5.py
qosm/gui/objects/pipeline.py
qosm/gui/tabs/ConstructionTab.py
qosm/gui/tabs/ParametersTab.py
qosm/gui/tabs/RequestsTab.py
qosm/gui/tabs/__init__.py
qosm/gui/view/GLViewer.py
qosm/gui/view/RequestViewer.py
qosm/gui/view/__init__.py
qosm/gui/view/opengl_viewer/gbtc.py
qosm/gui/view/opengl_viewer/objects.py
qosm/gui/view/opengl_viewer/requests.py
qosm/gui/view/opengl_viewer/sources.py
qosm/gui/view/requests/FarField.py
qosm/gui/view/requests/GBTC.py
qosm/gui/view/requests/NearField.py
qosm/gui/view/sources/NFSourceViewer.py
qosm/gui/workers/SimulationWorker.py
qosm/gui/workers/__init__.py
qosm/items/Mesh.py
qosm/items/MshMesh.py
qosm/items/ObjMesh.py
qosm-0.49.dist-info/METADATA
qosm-0.49.dist-info/WHEEL
qosm-0.49.dist-info/top_level.txt
qosm-0.49.dist-info/RECORD
qosm-0.49.dist-info/sboms/auditwheel.cdx.json
