Metadata-Version: 2.4
Name: qosm
Version: 0.49
Summary: Quasi-Optical System Modelling
Author-email: Gregory Gaudin <gregory.gaudin@imt-atlantique.fr>, Clement Henry <clement.henry@imt-atlantique.fr>
License-Expression: AFL-3.0
Requires-Python: >=3.11
Requires-Dist: matplotlib
Requires-Dist: numpy
Requires-Dist: scipy
Requires-Dist: gmsh
Requires-Dist: h5py
Requires-Dist: scikit-rf
Requires-Dist: pyside6
Requires-Dist: PyOpenGL
Requires-Dist: PyOpenGL-Accelerate
Requires-Dist: toml
Requires-Dist: tqdm
